pytest_filterfixtures/__init__.py
pytest_filterfixtures/plugin.py
pytest_filterfixtures-0.1.0.dist-info/WHEEL
pytest_filterfixtures-0.1.0.dist-info/entry_points.txt
pytest_filterfixtures-0.1.0.dist-info/METADATA
pytest_filterfixtures-0.1.0.dist-info/RECORD
