Metadata-Version: 2.3
Name: pytest-filterfixtures
Version: 0.1.0
Summary: pytest plugin to execute or ignore tests based on fixtures
Author: Ignacio Goldchluk
Classifier: Framework :: Pytest
Classifier: Intended Audience :: Developers
Classifier: Programming Language :: Python
Classifier: Programming Language :: Python :: 3 :: Only
Classifier: Topic :: Software Development :: Quality Assurance
Classifier: Topic :: Software Development :: Testing
Classifier: Topic :: Utilities
Requires-Dist: pytest>=9.0.2
Requires-Python: >=3.10
Project-URL: repository, https://github.com/IgnacioGoldchluk/pytest-filterfixtures
